distython/HEOM.py
distython/HVDM.py
distython/VDM.py
distython/__init__.py
distython/heom_example.py
distython-0.0.3.dist-info/LICENSE
distython-0.0.3.dist-info/METADATA
distython-0.0.3.dist-info/WHEEL
distython-0.0.3.dist-info/top_level.txt
distython-0.0.3.dist-info/RECORD
