Metadata-Version: 2.1
Name: distython
Version: 0.0.3
Summary: Implementation of state-of-the-art distance metrics from research papers which can handle mixed-type data and missing values.
Home-page: https://github.com/KacperKubara/distython
Author: Kacper Kubara
Author-email: kacper.kubara.ai@gmail.com
License: UNKNOWN
Platform: UNKNOWN
Classifier: Programming Language :: Python :: 3
Classifier: License :: OSI Approved :: MIT License
Classifier: Operating System :: OS Independent
